{
    "booklist": [
        {
            "id": 1,
            "book": "반야심경 (摩訶般若波羅蜜經)",
            "desc": "공(空)사상을 담은 경전으로 관세음보살이 부처가 진리를 보는 방법으로 세상을 보니 이치가 '색즉시공 공즉시색' 이라는 가르침을 주는 경전"
        },
        {
            "id": 2,
            "book": "금강경 (金剛般若波羅密經)",
            "desc": "반야로서 무주상보시(無住相布施)의 방법을 실행함으로써 보살이 되는 방법을 알려주는 경전"
        },
        {
            "id": 3,
            "book": "불설아미타경 (佛說阿彌陀經)",
            "desc": "아미타 부처와 극락정토의 장엄함을 설명하고 아미타 부처의 이름을 한마음으로 부르면 극락에 왕생한다는 경전"
        },
        {
            "id": 4,
            "book": "관세음보살보문품(觀世音菩薩普門品)",
            "desc": "대승불교의 보살사상을 가장 잘 대변하는 관세음보살의 성격과 공덕이 구체적으로 설명한 경전"
        }
    ]
}
